keras_efficient_kan/__init__.py
keras_efficient_kan/kan.py
keras_efficient_kan-0.1.10.dist-info/METADATA
keras_efficient_kan-0.1.10.dist-info/WHEEL
keras_efficient_kan-0.1.10.dist-info/RECORD
